gvision/GVISION_AUTOMATION.py
gvision/__init__.py
gvision/cli.py
gvision/pages/2_Object_Detection_Demo.py
gvision/pages/3_Classification_or_Pose_Demo.py
gvision-1.0.3.dist-info/METADATA
gvision-1.0.3.dist-info/WHEEL
gvision-1.0.3.dist-info/entry_points.txt
gvision-1.0.3.dist-info/top_level.txt
gvision-1.0.3.dist-info/RECORD
