Metadata-Version: 2.1
Name: gvision
Version: 1.0.3
Summary: End-to-end automation platform for computer vision projects.
Home-page: https://github.com/gaurang157/gvision
Author: Gaurang Ingle
Author-email: gaurang.ingle@gmail.com
Maintainer: Gaurang Ingle
Maintainer-email: gaurang.ingle@gmail.com
License: MIT
Project-URL: Bug Reports, https://github.com/gaurang157/gvision/issues
Project-URL: Source, https://github.com/gaurang157/gvision
Project-URL: Documentation, https://github.com/gaurang157/gvision/blob/main/README.md
Project-URL: Say Thanks!, https://github.com/gaurang157/gvision/issues/new?assignees=&labels=&template=thanks.yml
Keywords: computer vision,automation,model training,model deployment,object detection,segmentation,classification,pose estimation,deep learning,machine learning,Roboflow,Ultralytics,TensorFlow,TensorBoard,Streamlit,CLI interface,UI interface
Classifier: Programming Language :: Python :: 3
Classifier: Operating System :: OS Independent
Classifier: Development Status :: 4 - Beta
Classifier: Intended Audience :: End Users/Desktop
Classifier: Intended Audience :: Developers
Classifier: Intended Audience :: Education
Classifier: Natural Language :: English
Classifier: Topic :: Scientific/Engineering :: Artificial Intelligence
Classifier: Topic :: Software Development :: Libraries :: Application Frameworks
Classifier: Topic :: Software Development :: User Interfaces
Classifier: Topic :: Utilities
Requires-Python: >=3.8
Requires-Dist: av ==11.0.0
Requires-Dist: numpy ==1.24.4
Requires-Dist: opencv-python ==4.9.0.80
Requires-Dist: opencv-python-headless ==4.8.0.74
Requires-Dist: pandas ==2.0.3
Requires-Dist: Pillow ==10.2.0
Requires-Dist: PyYAML ==6.0.1
Requires-Dist: Requests ==2.31.0
Requires-Dist: roboflow ==1.1.1
Requires-Dist: streamlit ==1.31.1
Requires-Dist: streamlit-ace ==0.1.1
Requires-Dist: streamlit-webrtc ==0.47.1
Requires-Dist: supervision ==0.18.0
Requires-Dist: torch ==2.2.0
Requires-Dist: ultralytics ==8.1.10
Requires-Dist: YAML2ST ==1.0.20
Requires-Dist: tensorboard >=2.10.0
